pyvod/__init__.py
pyvod/__main__.py
pyvod/exceptions.py
pyvod/utils.py
pyvod/vod.py
pyvod/vodchat.py
pyvod/vodcomment.py
pyvod_chat-0.2.1.dist-info/LICENSE
pyvod_chat-0.2.1.dist-info/METADATA
pyvod_chat-0.2.1.dist-info/WHEEL
pyvod_chat-0.2.1.dist-info/top_level.txt
pyvod_chat-0.2.1.dist-info/RECORD
