Metadata-Version: 2.1
Name: pyvod-chat
Version: 0.2.1
Summary: A simple library and/or CLI tool for downloading a past Twitch.tv broadcast's (VOD) chat comments.
Home-page: https://github.com/sixP-NaraKa/pyvod-chat
Author: sixP-NaraKa
Author-email: sixpaths-naraka@protonmail.com
License: MIT
Platform: UNKNOWN
Classifier: License :: OSI Approved :: MIT License
Classifier: Operating System :: OS Independent
Classifier: Programming Language :: Python :: 3
Requires-Python: >=3.6
Requires-Dist: requests (>=2.20.0)
Requires-Dist: python-dotenv (>=0.10.0)
